streamlit_healthcheck/__init__.py
streamlit_healthcheck/healthcheck.py
streamlit_healthcheck/server.py
streamlit_healthcheck/streamlit-healthcheck-cli.py
streamlit_healthcheck-0.1.9.dist-info/licenses/LICENSE
streamlit_healthcheck-0.1.9.dist-info/METADATA
streamlit_healthcheck-0.1.9.dist-info/WHEEL
streamlit_healthcheck-0.1.9.dist-info/top_level.txt
streamlit_healthcheck-0.1.9.dist-info/RECORD
