Metadata-Version: 2.4
Name: streamlit-healthcheck
Version: 0.1.9
Summary: Comprehensive health monitoring for Streamlit apps: system, dependencies, custom checks, and page errors.
Author-email: Saradindu Sengupta <saradindu.mi1@iiitmk.ac.in>
License-Expression: GPL-3.0-or-later
Project-URL: Homepage, https://github.com/saradindusengupta/streamlit-healthcheck
Project-URL: Repository, https://github.com/saradindusengupta/streamlit-healthcheck
Project-URL: Documentation, https://saradindusengupta.co.in/streamlit-healthcheck/streamlit_healthcheck.html
Project-URL: Issues, https://github.com/saradindusengupta/streamlit-healthcheck/issues
Keywords: streamlit,healthcheck,system,monitoring,app,dashboard
Classifier: Programming Language :: Python :: 3
Classifier: Operating System :: OS Independent
Classifier: Development Status :: 4 - Beta
Classifier: Intended Audience :: Developers
Classifier: Topic :: Software Development :: Build Tools
Classifier: Topic :: Utilities
Requires-Python: >=3.11
License-File: LICENSE
Requires-Dist: streamlit
Requires-Dist: psutil
Requires-Dist: click
Requires-Dist: fastapi>=0.68.0
Requires-Dist: uvicorn>=0.15.0
Requires-Dist: joblib
Dynamic: license-file
